airworks_api/__init__.py
airworks_api/base_api.py
airworks_api/common_api.py
airworks-0.0.4.dist-info/LICENSE
airworks-0.0.4.dist-info/METADATA
airworks-0.0.4.dist-info/WHEEL
airworks-0.0.4.dist-info/top_level.txt
airworks-0.0.4.dist-info/RECORD
