Metadata-Version: 2.1
Name: airworks
Version: 0.0.4
Summary: Tools for airworks airworks_api sdk
Home-page: https://github.com/coder-baymax/airworks
Author: valuesimplex
License: UNKNOWN
Platform: UNKNOWN
Classifier: Development Status :: 3 - Alpha
Classifier: Intended Audience :: Developers
Classifier: Topic :: Software Development :: Build Tools
Classifier: License :: OSI Approved :: MIT License
Classifier: Programming Language :: Python :: 3
Requires-Python: >=3.5
